Metadata-Version: 2.1
Name: lyytkfunction
Version: 1.7
Summary: yyjdgui for lyy
Author: lyy
Author-email: 
License: MIT
License-File: LICENSE
